itly_plugin_schema_validator/__init__.py
itly_plugin_schema_validator/_schema_validator.py
itly_plugin_schema_validator-0.1.9.dist-info/WHEEL
itly_plugin_schema_validator-0.1.9.dist-info/METADATA
itly_plugin_schema_validator-0.1.9.dist-info/RECORD
